cdpred/Model/alt_model.pkl
cdpred/Model/main_model.pkl
cdpred/Model/motif_ensemble
cdpred/Python_scripts/__init__.py
cdpred/Python_scripts/cdpred.py
cdpred-1.1.dist-info/METADATA
cdpred-1.1.dist-info/WHEEL
cdpred-1.1.dist-info/entry_points.txt
cdpred-1.1.dist-info/top_level.txt
cdpred-1.1.dist-info/RECORD
