Metadata-Version: 2.1
Name: cdpred
Version: 1.1
Summary: A tool to predict celiac disease associated peptides
Home-page: https://gitlab.com/raghavalab/cdpred
Requires-Python: >=3.6
Requires-Dist: numpy
Requires-Dist: pandas
Requires-Dist: scikit-learn (==1.2.2)
